LICENSE.rst
MANIFEST.in
README.rst
setup.py
django_paranoia/__init__.py
django_paranoia/configure.py
django_paranoia/decorators.py
django_paranoia/flags.py
django_paranoia/forms.py
django_paranoia/middleware.py
django_paranoia/sessions.py
django_paranoia/signals.py
django_paranoia.egg-info/PKG-INFO
django_paranoia.egg-info/SOURCES.txt
django_paranoia.egg-info/dependency_links.txt
django_paranoia.egg-info/not-zip-safe
django_paranoia.egg-info/requires.txt
django_paranoia.egg-info/top_level.txt
django_paranoia/reporters/__init__.py
django_paranoia/reporters/cef_.py
django_paranoia/reporters/log.py