Metadata-Version: 1.0
Name: django-paranoia
Version: 0.1.8.7
Summary: OWASP detection point reporting for Django
Home-page: https://github.com/andymckay/django-paranoia
Author: Andy McKay
Author-email: andym@mozilla.com
License: BSD
Platform: UNKNOWN
Classifier: Intended Audience :: Developers
Classifier: Natural Language :: English
Classifier: Operating System :: OS Independent
Classifier: Framework :: Django
